conversationalnlp/__init__.py
conversationalnlp/models/__init__.py
conversationalnlp/models/intentclassification/__init__.py
conversationalnlp/models/intentclassification/labellingfunc.py
conversationalnlp/models/intentclassification/metadata/intentlut.csv
conversationalnlp/models/sentenceimportance/__init__.py
conversationalnlp/models/sentenceimportance/labellingfunc.py
conversationalnlp/models/sentenceimportance/modelloader.py
conversationalnlp/models/sentenceimportance/predict.py
conversationalnlp/models/sentenceimportance/metadata/keywords0.txt
conversationalnlp/models/wav2vec2/__init__.py
conversationalnlp/models/wav2vec2/datacollator.py
conversationalnlp/models/wav2vec2/datasanitycheck.py
conversationalnlp/models/wav2vec2/dataset.py
conversationalnlp/models/wav2vec2/fileprep.py
conversationalnlp/models/wav2vec2/modelloader.py
conversationalnlp/models/wav2vec2/predict.py
conversationalnlp/models/wav2vec2/wer.py
conversationalnlp/utils/__init__.py
conversationalnlp/utils/configloader.py
conversationalnlp/utils/customdatetime.py
conversationalnlp/utils/display.py
conversationalnlp/utils/filesys.py
conversationalnlp/utils/modeltracker.py
conversationalnlp/utils/sentencehandler.py
conversationalnlp-0.0.4.post1.dist-info/LICENSE
conversationalnlp-0.0.4.post1.dist-info/METADATA
conversationalnlp-0.0.4.post1.dist-info/WHEEL
conversationalnlp-0.0.4.post1.dist-info/top_level.txt
conversationalnlp-0.0.4.post1.dist-info/RECORD
